<?xml version="1.0" encoding="UTF-8" ?>

<!DOCTYPE struts-config PUBLIC "-//Apache Software Foundation//DTD Struts Configuration 1.2//EN" "http://jakarta.apache.org/struts/dtds/struts-config_1_2.dtd">

<struts-config> 

	<!-- ========== Data Sources Definitions =================================== -->
	<!--
		Define your Struts data sources in a file called struts-data-sources.xml and place
		it in your merge directory.
	-->

	<!-- ========== Form Bean Definitions =================================== -->
	<form-beans>
		<form-bean
       name="statForm"
       type="com.boco.eoms.commons.statistic.base.webapp.form.StatForm"
    /> 
   
	</form-beans>

	<!-- ========== Global Exceptions Definitions =================================== -->
	<global-exceptions>
		<exception type="java.lang.Exception" key="errors.general"
			handler="com.boco.eoms.base.webapp.action.ActionExceptionHandler" />
	</global-exceptions>

	<!-- ========== Global Forward Definitions =================================== -->
	<global-forwards>
		<forward name="selectFile" path="/selectFile.do" />
		<forward name="logout" path="/logout.jsp" />
      	<forward
          name="fail"
          path="/common/fail.jsp"
          redirect="false"
          contextRelative="true"
      	/>
	</global-forwards>

	<!-- ========== Action Mapping Definitions =================================== -->
	<action-mappings>
		<action path="/stat"
			type="com.boco.eoms.commons.statistic.sample.webapp.action.SampleAction"
			name="statForm" scope="request" parameter="method"
			unknown="false" validate="false" attribute="sampleStatMethod"> 
			<set-property property="cancellable" value="true" />

		      <forward name="statisticsheetlist"
			      path="/WEB-INF/pages/statistic/sample/statisticsheetlist.jsp" redirect="false"
		          contextRelative="true" /> 
		
		      <forward name="statistic" 
				  path="/WEB-INF/pages/statistic/sample/statistic.jsp" redirect="false"
				  contextRelative="true"/>
    
	         <forward name="statisticresult" 
		          path="/WEB-INF/pages/statistic/common/rowresult.jsp" redirect="false"
		          contextRelative="true"/> 		  
    </action>
		
	</action-mappings>

	<controller nocache="true" inputForward="true" maxFileSize="2M" />
	<message-resources parameter="config/statistic/base-config/ApplicationResources-statistic"
		key="statistic" />
	
	<!-- ========== Validator plugin ===================  -->
	<plug-in className="org.apache.struts.validator.ValidatorPlugIn">
		<set-property property="pathnames"
			value="/WEB-INF/validator-rules.xml,
                             /WEB-INF/validator-rules-custom.xml,
                             /WEB-INF/validation.xml" />
	</plug-in>

</struts-config>