<?xml version="1.0" encoding="UTF-8"?>

<KpiConfig>
	<title>kpi统计</title>
	<est-module-id>51</est-module-id>

	<!-- 按人员 -->
	<kpi-define>
		<name>commonfault_intime_byuser</name>
		<kpi-caption></kpi-caption>
		<!-- dbtype={String,int,datetime} -->
		<condition-param page-name="beginTime"/>
		<condition-param page-name="endTime"/>
		<condition-param  page-name="areaid" markflg="true"/>
		<condition-param  page-name="mainNetSortOne" markflg="true"/>
		<condition-param  page-name="mainNetSortTwo" markflg="true"/>
		<condition-param  page-name="mainNetSortThree" markflg="true"/>
		<condition-param  page-name="userByDeptid" markflg="true"/>

		<summary-define>
			<id>s1</id>
			<sequence></sequence>
			<column>est.OPERATEUSERID</column>
			<id2name-service>statBaseUserId2name_v35</id2name-service>
		</summary-define>

		<summary-define>
			<id>s2</id>
			<sequence></sequence>
			<column>est.mainNetSortOne</column>
			<id2name-service>statDictId2name_v35</id2name-service>
		</summary-define>
			<summary-define>
			<id>s3</id>
			<sequence></sequence>
			<column>est.mainNetSortTwo</column>
			<id2name-service>statDictId2name_v35</id2name-service>
		</summary-define>
		<summary-define>
			<id>s4</id>
			<sequence></sequence>
			<column>est.mainNetSortThree</column>
			<id2name-service>statDictId2name_v35</id2name-service>
		</summary-define>
		<summary-define>
			<id>s5</id>
			<sequence></sequence>
			<column>est.TODEPTID</column>
			<id2name-service>statAreaId2name_v35</id2name-service>
			
		</summary-define>

		<stat-detail-vo>com.boco.eoms.commons.statistic.commonfault.vo.CommonfaultDetailVO</stat-detail-vo>

		<query-define>
			<name>query1</name>
			
			<from>EST_COMMONFAULT est</from>
			<where>est.ENDTIME&gt;'@beginTime@' and est.ENDTIME&lt;'@endTime@' and est.status=1  and (est.maindelayflag='' or est.maindelayflag is null) and (est.mainifrecord is null or est.mainifrecord=0)  
			and est.OPERATEUSERID in (@userByDeptid@) and est.OPERATEUSERID is not null and est.mainNetSortOne in (@mainNetSortOne@) 
			 and est.mainNetSortTwo in (@mainNetSortTwo@) and est.mainNetSortThree in (@mainNetSortThree@) and est.TODEPTID in (@areaid@) and est.operatetype in (46, 61)</where><!-- ???为空 -->
			<order-by></order-by>

			<field-define>
				<id>f1</id>
				<sequence>1</sequence>

				<stat-type>field_sql</stat-type><!--"field_sql,expression"  -->
				<stat-sql>count(distinct est.mainid)</stat-sql>
				<list-count-select-sql>select count(distinct est.mainid) </list-count-select-sql>
				<list-hsql>
					select distinct est.mainid ,est.sheetid,est.title, est.senduserid, est.senddeptid ,est.sendtime from EST_COMMONFAULT est where 
 					est.ENDTIME&gt;'@beginTime@' and est.ENDTIME&lt;'@endTime@'
 					and est.status=1  and (est.maindelayflag='' or est.maindelayflag is null) and (est.mainifrecord is null or est.mainifrecord=0)  
 					and est.OPERATEUSERID='@s1@' and est.mainNetSortOne='@s2@'  and est.mainNetSortTwo='@s3@' and est.mainNetSortThree='@s4@' 
 					and est.TODEPTID='@s5@' and est.operatetype in (46, 61)
				</list-hsql>
				
			</field-define>
			
		</query-define>
		
		<query-define>
			<name>query2</name>
			
			<from>EST_COMMONFAULT est</from>
			<where>
			est.ENDTIME&gt;'@beginTime@' and est.ENDTIME&lt;'@endTime@' and est.status=1 and (est.maindelayflag='' or est.maindelayflag is null) and est.operatetype in(46,61) and est.completeflag=2  and (est.maindelayflag='' or est.maindelayflag is null) and (est.mainifrecord is null or est.mainifrecord=0) 
			and est.OPERATEUSERID in (@userByDeptid@) and est.OPERATEUSERID is not null and est.mainNetSortOne in (@mainNetSortOne@) 
				and est.mainNetSortTwo in (@mainNetSortTwo@) and est.mainNetSortThree in (@mainNetSortThree@) and est.TODEPTID in (@areaid@)
			</where>
			<order-by></order-by>

			<field-define>
				<id>f2</id>
				<sequence>1</sequence>

				<stat-type>field_sql</stat-type><!--"field_sql,expression"  -->
				<stat-sql>count(distinct est.mainid)</stat-sql>
				<list-count-select-sql>select count(distinct est.mainid) </list-count-select-sql>
				
				<list-hsql>
					select distinct est.mainid ,est.sheetid,est.title, est.senduserid, est.senddeptid ,est.sendtime from EST_COMMONFAULT est where 
					est.ENDTIME&gt;'@beginTime@' and est.ENDTIME&lt;'@endTime@'
					and est.status=1  and est.operatetype in(46,61) and est.completeflag=2  and (est.maindelayflag='' or est.maindelayflag is null) and (est.mainifrecord is null or est.mainifrecord=0) 
					and est.OPERATEUSERID='@s1@' and est.mainNetSortOne='@s2@' and est.TODEPTID='@s5@'  and est.mainNetSortTwo='@s3@' and est.mainNetSortThree='@s4@' 
				</list-hsql>
				
			</field-define>

			<field-define><!-- 可重复 -->
				<id>f3</id><!-- 及时工单 -->
				<sequence>1</sequence>

				<stat-type>expression</stat-type><!--"field_sql,single_sql,expression"  -->
				<stat-sql>new Integer(f1)--new Integer(f2)</stat-sql>
<list-count-select-sql>select count(distinct est.mainid) </list-count-select-sql>
				<list-hsql>
				select distinct est.mainid ,est.sheetid,est.title, est.senduserid, est.senddeptid ,est.sendtime from EST_COMMONFAULT est where 
 					est.ENDTIME&gt;'@beginTime@' and est.ENDTIME&lt;'@endTime@'
 					and est.status=1  and (est.maindelayflag='' or est.maindelayflag is null) and (est.mainifrecord is null or est.mainifrecord=0)  
 					and est.OPERATEUSERID='@s1@' and est.mainNetSortOne='@s2@'  and est.mainNetSortTwo='@s3@' and est.mainNetSortThree='@s4@' and est.TODEPTID='@s5@' and est.operatetype in (46, 61)
 				and est.mainid not in (select distinct est1.mainid from EST_COMMONFAULT est1 where 
					est1.ENDTIME&gt;'@beginTime@' and est1.ENDTIME&lt;'@endTime@'
					and est1.status=1 and est1.operatetype in(46,61) and est1.completeflag=2  and (est1.maindelayflag='' or est1.maindelayflag is null) and (est1.mainifrecord is null or est1.mainifrecord=0) 
					and est1.OPERATEUSERID='@s1@' and est1.mainNetSortOne='@s2@'  and est1.mainNetSortTwo='@s3@' and est1.mainNetSortThree='@s4@' and est1.TODEPTID='@s5@')	
				</list-hsql>
			</field-define>	

		</query-define>
		
	</kpi-define>
	

	
	<!-- 按角色 -->
	<kpi-define>
		<name>commonfault_intime_byrole</name>
		<kpi-caption></kpi-caption>
		
		<condition-param page-name="beginTime"/>
		<condition-param page-name="endTime"/>
		<condition-param  page-name="areaid" markflg="true"/>
		<condition-param  page-name="mainNetSortOne" markflg="true"/>
		<condition-param  page-name="mainNetSortTwo" markflg="true"/>
		<condition-param  page-name="mainNetSortThree" markflg="true"/>
		<condition-param  page-name="subroleFromDeptid" markflg="true"/>
		
		<summary-define>
			<id>s1</id>
			<sequence></sequence>
			<column>est.OPERATEROLEID</column>
			<id2name-service>statSubRoleId2name_v35</id2name-service>
		</summary-define>

		<summary-define>
			<id>s2</id>
			<sequence></sequence>
			<column>est.mainNetSortOne</column>
			<id2name-service>statDictId2name_v35</id2name-service>
		</summary-define>
			<summary-define>
			<id>s3</id>
			<sequence></sequence>
			<column>est.mainNetSortTwo</column>
			<id2name-service>statDictId2name_v35</id2name-service>
		</summary-define>
		<summary-define>
			<id>s4</id>
			<sequence></sequence>
			<column>est.mainNetSortThree</column>
			<id2name-service>statDictId2name_v35</id2name-service>
		</summary-define>
		<summary-define>
			<id>s5</id>
			<sequence></sequence>
			<column>est.TODEPTID</column>
			<!--id2name-service>tawSystemDeptDao</id2name-service-->
			<id2name-service>statAreaId2name_v35</id2name-service>
		</summary-define>

		<stat-detail-vo>com.boco.eoms.commons.statistic.commonfault.vo.CommonfaultDetailVO</stat-detail-vo>

		<query-define>
			<name>query1</name>
			<from>EST_COMMONFAULT est</from>
			<where>est.ENDTIME&gt;'@beginTime@' and est.ENDTIME&lt;'@endTime@' and  est.status=1 and (est.maindelayflag='' or est.maindelayflag is null) and (est.mainifrecord is null or est.mainifrecord=0)   
			and est.OPERATEROLEID in (@subroleFromDeptid@) and est.OPERATEROLEID is not null and est.mainNetSortOne in (@mainNetSortOne@) 
				and est.mainNetSortTwo in (@mainNetSortTwo@) and est.mainNetSortThree in (@mainNetSortThree@) and est.TODEPTID in (@areaid@) and est.operatetype in (46, 61) and LENGTH(est.operateroleid)=32</where>
			<order-by></order-by>

			<field-define>
				<id>f1</id>
				<sequence>1</sequence>

				<stat-type>field_sql</stat-type><!--"field_sql,expression"  -->
				<stat-sql>count(distinct est.mainid)</stat-sql>
				<list-count-select-sql>select count(distinct est.mainid) </list-count-select-sql>
				<list-hsql>
					select distinct est.mainid ,est.sheetid,est.title, est.senduserid, est.senddeptid ,est.sendtime from EST_COMMONFAULT est where 
 					est.ENDTIME&gt;'@beginTime@' and est.ENDTIME&lt;'@endTime@'
 					and  est.status=1 and (est.maindelayflag='' or est.maindelayflag is null) and (est.mainifrecord is null or est.mainifrecord=0) 
 					and est.OPERATEROLEID='@s1@' and est.mainNetSortOne='@s2@'  and est.mainNetSortTwo='@s3@' and est.mainNetSortThree='@s4@' 
 					and est.TODEPTID='@s5@' and est.operatetype in (46, 61) and LENGTH(est.operateroleid)=32
				</list-hsql>
				
			</field-define>
			
		</query-define>
	
		
		<query-define>
			<name>query2</name>
			
			<from>EST_COMMONFAULT est</from>
			<where> est.ENDTIME&gt;'@beginTime@' and est.ENDTIME&lt;'@endTime@' and est.status=1 and 
			(est.maindelayflag='' or est.maindelayflag is null) and est.operatetype in (46, 61) 
			and est.completeflag=2 and (est.mainifrecord is null or est.mainifrecord=0) and LENGTH(est.operateroleid)=32 	
			and est.OPERATEROLEID in (@subroleFromDeptid@) and est.OPERATEROLEID is not null and est.mainNetSortOne in (@mainNetSortOne@)
				and est.mainNetSortTwo in (@mainNetSortTwo@) and est.mainNetSortThree in (@mainNetSortThree@) and est.TODEPTID in (@areaid@)
				</where>
			<order-by></order-by>

			<field-define>
				<id>f2</id>
				<sequence>1</sequence>

				<stat-type>field_sql</stat-type><!--"field_sql,expression"  -->
				<stat-sql>count(distinct est.mainid)</stat-sql>
				<list-count-select-sql>select count(distinct est.mainid) </list-count-select-sql>
				
				<list-hsql>
					select distinct est.mainid ,est.sheetid,est.title, est.senduserid, est.senddeptid ,est.sendtime from EST_COMMONFAULT est where 
					est.ENDTIME&gt;'@beginTime@' and est.ENDTIME&lt;'@endTime@'
					and est.status=1 and (est.maindelayflag='' or est.maindelayflag is null) and est.operatetype in (46, 61) and est.completeflag=2 and (est.mainifrecord is null or est.mainifrecord=0) 
					and est.OPERATEROLEID='@s1@' and est.mainNetSortOne='@s2@'  and est.mainNetSortTwo='@s3@' and est.mainNetSortThree='@s4@' 
					and est.TODEPTID='@s5@' and LENGTH(est.operateroleid)=32
				</list-hsql>
				
			</field-define>
			

<field-define><!-- 可重复 -->
				<id>f3</id><!-- 及时工单 -->
				<sequence>1</sequence>

				<stat-type>expression</stat-type><!--"field_sql,single_sql,expression"  -->
				<stat-sql>new Integer(f1)--new Integer(f2)</stat-sql>
<list-count-select-sql>select count(distinct est.mainid) </list-count-select-sql>
				<list-hsql>
				select distinct est.mainid ,est.sheetid,est.title, est.senduserid, est.senddeptid ,est.sendtime from EST_COMMONFAULT est where 
 					est.ENDTIME&gt;'@beginTime@' and est.ENDTIME&lt;'@endTime@'
 					and  est.status=1 and (est.maindelayflag='' or est.maindelayflag is null) and (est.mainifrecord is null or est.mainifrecord=0) 
 					and est.OPERATEROLEID='@s1@' and est.mainNetSortOne='@s2@' and est.TODEPTID='@s5@'  and est.mainNetSortTwo='@s3@' and est.mainNetSortThree='@s4@' 
 					and est.operatetype in (46, 61) and LENGTH(est.operateroleid)=32 
 				and est.mainid not in (select distinct est1.mainid from EST_COMMONFAULT est1 where 
					est1.ENDTIME&gt;'@beginTime@' and est1.ENDTIME&lt;'@endTime@'
					and est1.status=1 and (est1.maindelayflag='' or est1.maindelayflag is null) and est1.operatetype in(46,61) and est1.completeflag=2 and (est1.mainifrecord is null or est1.mainifrecord=0) 
					and est1.OPERATEROLEID='@s1@' and est1.mainNetSortOne='@s2@'  and est1.mainNetSortTwo='@s3@' and est1.mainNetSortThree='@s4@' 
					and est1.TODEPTID='@s5@' and LENGTH(est1.operateroleid)=32)	
				</list-hsql>
			</field-define>			
			

		</query-define>
		
	</kpi-define>
	
</KpiConfig>