<?xml version="1.0" encoding="UTF-8"?>
<layout>
    <cell id="1" type="InitialActionCell" height="30" width="100" x="187" y="83"/>
    <cell id="2" type="StepCell" height="30" width="100" x="660" y="83"/>
    <cell id="3" type="StepCell" height="30" width="100" x="1016" y="83"/>
    <cell id="4" type="StepCell" height="30" width="100" x="413" y="290"/>
    <cell id="5" type="StepCell" height="30" width="100" x="615" y="489"/>
    <cell id="6" type="StepCell" height="30" width="100" x="827" y="681"/>
    <cell id="7" type="StepCell" height="30" width="100" x="1016" y="895"/>
    <connector id="90" linewidth="1.0" color="-16777216" labelx="994" labely="438" from="0" to="0" start="187,83"
               end="413,290">
        <routing id="90" x="461" y="105"/>
    </connector>
    <connector id="91" linewidth="1.0" color="-16777216" labelx="552" labely="0" from="0" to="0" start="187,83"
               end="660,83"/>
    <connector id="92" linewidth="1.0" color="-16777216" labelx="2" labely="520" from="0" to="0" start="187,83"
               end="827,681">
        <routing id="92" x="237" y="700"/>
    </connector>
    <connector id="93" linewidth="1.0" color="-16777216" labelx="1000" labely="427" from="0" to="0" start="413,290"
               end="615,489">
        <routing id="93" x="662" y="304"/>
    </connector>
    <connector id="94" linewidth="1.0" color="-16777216" labelx="676" labely="0" from="0" to="0" start="413,290"
               end="1016,83">
        <routing id="94" x="1029" y="305"/>
    </connector>
    <connector id="95" linewidth="1.0" color="-16777216" labelx="1000" labely="444" from="0" to="0" start="615,489"
               end="827,681">
        <routing id="95" x="877" y="503"/>
    </connector>
    <connector id="96" linewidth="1.0" color="-16777216" labelx="1000" labely="508" from="0" to="0" start="615,489"
               end="413,290">
        <routing id="96" x="463" y="505"/>
    </connector>
    <connector id="97" linewidth="1.0" color="-16777216" labelx="1000" labely="434" from="0" to="0" start="827,681"
               end="1016,895">
        <routing id="97" x="1044" y="697"/>
    </connector>
    <connector id="98" linewidth="1.0" color="-16777216" labelx="1006" labely="450" from="0" to="0" start="827,681"
               end="615,489">
        <routing id="98" x="664" y="690"/>
    </connector>
    <connector id="99" linewidth="1.0" color="-16777216" labelx="974" labely="443" from="0" to="0" start="827,681"
               end="1016,83">
        <routing id="99" x="1043" y="686"/>
    </connector>
    <connector id="910" linewidth="1.0" color="-16777216" labelx="0" labely="659" from="0" to="0" start="1016,895"
               end="1016,83"/>
    <connector id="911" linewidth="1.0" color="-16777216" labelx="993" labely="492" from="0" to="0" start="1016,895"
               end="827,681">
        <routing id="911" x="878" y="908"/>
    </connector>
    <channel id="chl-1" y1="0" y2="200" text="建单人"/>
    <channel id="chl-2" y1="200" y2="400" text="设备维护人"/>
    <channel id="chl-3" y1="400" y2="600" text="厂家"/>
    <channel id="chl-4" y1="600" y2="800" text="报修人"/>
    <channel id="chl-5" y1="800" y2="1000" text="主管领导"/>
</layout>

