<?xml version="1.0" encoding="UTF-8"?>

<!DOCTYPE hibernate-mapping PUBLIC
    "-//Hibernate/Hibernate Mapping DTD 3.0//EN" 
    "http://hibernate.sourceforge.net/hibernate-mapping-3.0.dtd">

<hibernate-mapping

>

    <class
            name="com.boco.eoms.sheet.mofficedata.model.MofficeDataProMatch"
            table="mofficedata_promatch"
    >

    <id
        name="id"
            column="id">

    <!-- The generator-class attribute of @hibernate.id is deprecated, use the @hibernate.generator tag instead -->
    <generator class="assigned">

    </generator>

    </id>
        <property name="mainId" />
        <property name="buissType" />
		<property name="majorType" />
		<property name="producerId" />
        <property name="producerName" />
		<property name="createTime" />
		<property name="producerType" />
        <property name="netId" />
		<property name="netName" />
		<property name="deviceName" />
        <property name="deviceId" />
		<property name="accessories" />		
		<property name="correKey" />
		<property name="phaseName" />	
		<property name="rejectPhaseName" />		
		<property name="linkId" />
		
		<property name="mainStyle6" />	
		<property name="mainStyle7" />	
		<property name="mainStyle8" />	
		<property name="mainStyle9" />	
		<property name="mainStyle10" />			
</class>    
</hibernate-mapping>